sui_data/__init__.py
sui_data/__main__.py
sui_data/console.py
sui_data/cli/__init__.py
sui_data/cli/cli.py
sui_data/cli/download.py
sui_data/reports/__init__.py
sui_data/reports/billing.py
sui_data/reports/tc1_validated.py
sui_data-0.1.4.dist-info/LICENSE
sui_data-0.1.4.dist-info/METADATA
sui_data-0.1.4.dist-info/WHEEL
sui_data-0.1.4.dist-info/entry_points.txt
sui_data-0.1.4.dist-info/top_level.txt
sui_data-0.1.4.dist-info/RECORD
