Metadata-Version: 2.1
Name: sui_data
Version: 0.1.4
Summary: scrap Sistema Único de Información de Servicios Públicos Domiciliarios
Author-email: Example Author <jtamayoh@gmail.com>
Project-URL: Homepage, https://github.com/pypa/sampleproject
Project-URL: Issues, https://github.com/pypa/sampleproject/issues
Classifier: Programming Language :: Python :: 3
Classifier: License :: OSI Approved :: MIT License
Classifier: Operating System :: OS Independent
Requires-Python: >=3.8
License-File: LICENSE
Requires-Dist: typer
Requires-Dist: rich
Requires-Dist: pandas
Requires-Dist: httpx
Requires-Dist: pydantic
